FreeAeonFractal/FA1DMFS.py
FreeAeonFractal/FA2DMFS.py
FreeAeonFractal/FAImage.py
FreeAeonFractal/FAImageDimension.py
FreeAeonFractal/FAImageFourier.py
FreeAeonFractal/FASample.py
FreeAeonFractal/FAVisual.py
FreeAeonFractal/__init__.py
freeaeon_fractal-0.3.0.dist-info/licenses/LICENSE
freeaeon_fractal-0.3.0.dist-info/METADATA
freeaeon_fractal-0.3.0.dist-info/WHEEL
freeaeon_fractal-0.3.0.dist-info/top_level.txt
freeaeon_fractal-0.3.0.dist-info/RECORD
