Metadata-Version: 2.4
Name: FreeAeon-Fractal
Version: 0.3.0
Summary: Toolkit for Multifractal Analysis
Home-page: https://github.com/jim-xie-cn/FreeAeon-Fractal
Author: Jim Xie
Author-email: jim.xie.cn@outlook.com
Classifier: Programming Language :: Python :: 3
Classifier: License :: OSI Approved :: MIT License
Classifier: Operating System :: OS Independent
Requires-Python: >=3.6
License-File: LICENSE
Requires-Dist: numpy
Requires-Dist: matplotlib
Requires-Dist: tqdm
Requires-Dist: scikit-image
Requires-Dist: opencv-python
Requires-Dist: pandas
Requires-Dist: seaborn
Requires-Dist: scipy
Requires-Dist: MFDFA
Dynamic: author
Dynamic: author-email
Dynamic: classifier
Dynamic: description
Dynamic: description-content-type
Dynamic: home-page
Dynamic: license-file
Dynamic: requires-dist
Dynamic: requires-python
Dynamic: summary
